[
  {
    "title": "怠けがちな警察官の親切",
    "nickname": "Molru",
    "date": "2022-10-23 22:26:07",
    "replyNo": 4,
    "replyGroup": 4,
    "chars": [115]
  },
  [
    {
      "type": "chat",
      "replyNo": 0,
      "replyGroup": 0,
      "replyDepth": 0,
      "sCharacter": { "no": 115, "index": 1 },
      "content": "暇だぁ……",
      "isFirst": true,
      "file": ""
    },
    {
      "type": "chat",
      "replyNo": 0,
      "replyDepth": 0,
      "replyGroup": 0,
      "sCharacter": { "no": 115, "index": 1 },
      "content": "一通り手元のゲーム類も堪能したことだし、退屈……",
      "isFirst": true,
      "file": ""
    },
    {
      "type": "reply",
      "replyNo": 1,
      "replyGroup": 1,
      "replyDepth": 0,
      "sCharacter": { "no": 0, "index": 1 },
      "content": "じゃああらためて仕事とかどう？",
      "isFirst": true,
      "file": ""
    },
    {
      "type": "chat",
      "replyNo": 0,
      "replyGroup": 0,
      "replyDepth": 0,
      "sCharacter": { "no": 115, "index": 1 },
      "content": "それは絶対嫌。いっそ「何もしない」ということを始めよっかな……",
      "isFirst": true,
      "file": ""
    },
    {
      "type": "chat",
      "replyNo": 0,
      "replyGroup": 0,
      "replyDepth": 0,
      "sCharacter": { "no": 115, "index": 1 },
      "content": "そもそも今は、何も仕事無いし",
      "isFirst": false,
      "file": ""
    },
    {
      "type": "reply",
      "replyNo": 2,
      "replyGroup": 2,
      "replyDepth": 0,
      "sCharacter": { "no": 0, "index": 1 },
      "content": "生活安全局って、普段は何してるの？",
      "isFirst": true,
      "file": ""
    },
    {
      "type": "chat",
      "replyNo": 0,
      "replyGroup": 0,
      "replyDepth": 0,
      "sCharacter": { "no": 115, "index": 1 },
      "content": "普段、ねぇ……",
      "isFirst": true,
      "file": ""
    },
    {
      "type": "chat",
      "replyNo": 0,
      "replyGroup": 0,
      "replyDepth": 0,
      "sCharacter": { "no": 115, "index": 1 },
      "content": "そもそも生活安全局には、そんなに仕事とか来ないからなー",
      "isFirst": false,
      "file": ""
    },
    {
      "type": "chat",
      "replyNo": 0,
      "replyDepth": 0,
      "replyGroup": 0,
      "sCharacter": { "no": 115, "index": 1 },
      "content": "キリノは自分から仕事を作りに行くけど、基本は座って待機だよ",
      "isFirst": true,
      "file": ""
    },
    {
      "type": "chat",
      "replyNo": 0,
      "replyGroup": 0,
      "replyDepth": 0,
      "sCharacter": { "no": 115, "index": 1 },
      "content": "強いて言えば昼寝とか",
      "isFirst": false,
      "file": ""
    },
    {
      "type": "reply",
      "replyNo": 3,
      "replyGroup": 3,
      "replyDepth": 0,
      "sCharacter": { "no": 0, "index": 1 },
      "content": "それは仕事じゃないでしょ",
      "isFirst": true,
      "file": ""
    },
    {
      "type": "heart",
      "replyNo": 0,
      "replyGroup": 0,
      "replyDepth": 0,
      "sCharacter": { "no": 115, "index": 1 },
      "content": "",
      "isFirst": false,
      "file": ""
    }
  ]
]
