[
  {
    "title": "어른이 되고 싶은 이유(번역)",
    "nickname": "Molru",
    "date": "2022-10-27 01:37:25",
    "replyNo": 7,
    "replyGroup": 6,
    "chars": [88]
  },
  [
    {
      "type": "chat",
      "replyNo": 0,
      "replyGroup": 0,
      "replyDepth": 0,
      "sCharacter": { "no": 88, "index": 1 },
      "content": "얏-호! 선생님선생님!",
      "isFirst": true,
      "file": ""
    },
    {
      "type": "chat",
      "replyNo": 0,
      "replyDepth": 0,
      "replyGroup": 0,
      "sCharacter": { "no": 88, "index": 1 },
      "content": "뭐 하고 있어? 오늘 놀러…가 아니라.",
      "isFirst": true,
      "file": ""
    },
    {
      "type": "chat",
      "replyNo": 0,
      "replyGroup": 0,
      "replyDepth": 0,
      "sCharacter": { "no": 88, "index": 1 },
      "content": "멋진 레이디가 되기 위한 수행! 나, 하러 가도 돼?",
      "isFirst": false,
      "file": ""
    },
    {
      "type": "reply",
      "replyNo": 1,
      "replyGroup": 1,
      "replyDepth": 0,
      "sCharacter": { "no": 0, "index": 1 },
      "content": "미안, 카에데. 오늘은 일 때문에 조금 바빠서….",
      "isFirst": true,
      "file": ""
    },
    {
      "type": "chat",
      "replyNo": 0,
      "replyGroup": 0,
      "replyDepth": 0,
      "sCharacter": { "no": 88, "index": 1 },
      "content": "어? 오늘도 일하는 거야? 선생님은 보면 맨날 일만 하는 거 같아!",
      "isFirst": true,
      "file": ""
    },
    {
      "type": "chat",
      "replyNo": 0,
      "replyGroup": 0,
      "replyDepth": 0,
      "sCharacter": { "no": 88, "index": 1 },
      "content": "선생님은 일이 그렇게 좋아?",
      "isFirst": false,
      "file": ""
    },
    {
      "type": "reply",
      "replyNo": 2,
      "replyGroup": 2,
      "replyDepth": 0,
      "sCharacter": { "no": 0, "index": 1 },
      "content": "그, 글쎄. 어떠려나…….",
      "isFirst": true,
      "file": ""
    },
    {
      "type": "reply",
      "replyNo": 3,
      "replyGroup": 2,
      "replyDepth": 0,
      "sCharacter": { "no": 0, "index": 1 },
      "content": "서류 작업 자체는 좋아하지 않습니다…….",
      "isFirst": false,
      "file": ""
    },
    {
      "type": "chat",
      "replyNo": 0,
      "replyGroup": 0,
      "replyDepth": 0,
      "sCharacter": { "no": 88, "index": 1 },
      "content": "으음~ 그러면…. 아, 맞아! 나 들은 적 있어!",
      "isFirst": true,
      "file": ""
    },
    {
      "type": "chat",
      "replyNo": 0,
      "replyGroup": 0,
      "replyDepth": 0,
      "sCharacter": { "no": 88, "index": 1 },
      "content": "어른은 가끔 하기 싫은 일도 꾸역꾸역해야만 할 때가 있다고…. ",
      "isFirst": false,
      "file": ""
    },
    {
      "type": "chat",
      "replyNo": 0,
      "replyDepth": 0,
      "replyGroup": 0,
      "sCharacter": { "no": 88, "index": 1 },
      "content": "핫?! 어른이란 정말 힘든 거구나!",
      "isFirst": true,
      "file": ""
    },
    {
      "type": "chat",
      "replyNo": 0,
      "replyDepth": 0,
      "replyGroup": 0,
      "sCharacter": { "no": 88, "index": 1 },
      "content": "어라, 근데…. 선생님을 보고 있으면 가끔이 아닌 거 같은데….",
      "isFirst": true,
      "file": ""
    },
    {
      "type": "reply",
      "replyNo": 4,
      "replyGroup": 3,
      "replyDepth": 0,
      "sCharacter": { "no": 0, "index": 1 },
      "content": "큭! 아무렇지도 않게 날아오는 비수가 아파!",
      "isFirst": true,
      "file": ""
    },
    {
      "type": "chat",
      "replyNo": 0,
      "replyGroup": 0,
      "replyDepth": 0,
      "sCharacter": { "no": 88, "index": 1 },
      "content": "으음, 잘은 모르겠지만. ",
      "isFirst": true,
      "file": ""
    },
    {
      "type": "chat",
      "replyNo": 0,
      "replyDepth": 0,
      "replyGroup": 0,
      "sCharacter": { "no": 88, "index": 1 },
      "content": "…아! 좋은 생각이 났다!",
      "isFirst": true,
      "file": ""
    },
    {
      "type": "reply",
      "replyNo": 5,
      "replyGroup": 4,
      "replyDepth": 0,
      "sCharacter": { "no": 0, "index": 1 },
      "content": "응? 카에데?",
      "isFirst": true,
      "file": ""
    },
    {
      "type": "chat",
      "replyNo": 0,
      "replyGroup": 0,
      "replyDepth": 0,
      "sCharacter": { "no": 88, "index": 1 },
      "content": "후후후, 좋았어! 기다려줘! 선생님!",
      "isFirst": true,
      "file": ""
    },
    {
      "type": "chat",
      "replyNo": 0,
      "replyGroup": 0,
      "replyDepth": 0,
      "sCharacter": { "no": 88, "index": 1 },
      "content": "오늘은 선생님을 방해하지 않고, 착실하게 돕는 카에데 모드로 변신할 테니까!",
      "isFirst": false,
      "file": ""
    },
    {
      "type": "chat",
      "replyNo": 0,
      "replyDepth": 0,
      "replyGroup": 0,
      "sCharacter": { "no": 88, "index": 1 },
      "content": "그럼 이따가 봐!",
      "isFirst": true,
      "file": ""
    },
    {
      "type": "reply",
      "replyNo": 6,
      "replyGroup": 5,
      "replyDepth": 0,
      "sCharacter": { "no": 0, "index": 1 },
      "content": "응? 카에데?",
      "isFirst": true,
      "file": ""
    },
    {
      "type": "heart",
      "replyNo": 0,
      "replyGroup": 0,
      "replyDepth": 0,
      "sCharacter": { "no": 88, "index": 1 },
      "content": "",
      "isFirst": false,
      "file": ""
    }
  ]
]
