[
  {
    "title": "何するつもり？",
    "nickname": "Molru",
    "date": "2022-10-23 16:52:13",
    "replyNo": 6,
    "replyGroup": 4,
    "chars": [64]
  },
  [
    {
      "type": "chat",
      "replyNo": 0,
      "replyGroup": 0,
      "replyDepth": 0,
      "sCharacter": { "no": 64, "index": 1 },
      "content": "先生……？",
      "isFirst": true,
      "file": ""
    },
    {
      "type": "chat",
      "replyNo": 0,
      "replyDepth": 0,
      "replyGroup": 0,
      "sCharacter": { "no": 64, "index": 1 },
      "content": "今、時間大丈夫？",
      "isFirst": true,
      "file": ""
    },
    {
      "type": "chat",
      "replyNo": 0,
      "replyGroup": 0,
      "replyDepth": 0,
      "sCharacter": { "no": 64, "index": 1 },
      "content": "時間、あるよね？",
      "isFirst": false,
      "file": ""
    },
    {
      "type": "chat",
      "replyNo": 0,
      "replyGroup": 0,
      "replyDepth": 0,
      "sCharacter": { "no": 64, "index": 1 },
      "content": "どうせ、何もやってないでしょ……？",
      "isFirst": false,
      "file": ""
    },
    {
      "type": "reply",
      "replyNo": 1,
      "replyGroup": 1,
      "replyDepth": 0,
      "sCharacter": { "no": 0, "index": 1 },
      "content": "いや……ずっと仕事してたよ……",
      "isFirst": true,
      "file": ""
    },
    {
      "type": "reply",
      "replyNo": 2,
      "replyGroup": 1,
      "replyDepth": 0,
      "sCharacter": { "no": 0, "index": 1 },
      "content": "徹夜で全然寝てなくって、寝ようとしてたとこ……",
      "isFirst": false,
      "file": ""
    },
    {
      "type": "chat",
      "replyNo": 0,
      "replyGroup": 0,
      "replyDepth": 0,
      "sCharacter": { "no": 64, "index": 1 },
      "content": "……ふうん",
      "isFirst": true,
      "file": ""
    },
    {
      "type": "chat",
      "replyNo": 0,
      "replyGroup": 0,
      "replyDepth": 0,
      "sCharacter": { "no": 64, "index": 1 },
      "content": "と、とにかく",
      "isFirst": false,
      "file": ""
    },
    {
      "type": "chat",
      "replyNo": 0,
      "replyGroup": 0,
      "replyDepth": 0,
      "sCharacter": { "no": 64, "index": 1 },
      "content": "この前のこともあるし、ちょっと来て欲しいんだけど……",
      "isFirst": false,
      "file": ""
    },
    {
      "type": "reply",
      "replyNo": 4,
      "replyGroup": 3,
      "replyDepth": 0,
      "sCharacter": { "no": 0, "index": 1 },
      "content": "何……また監視するって言うの？",
      "isFirst": true,
      "file": ""
    },
    {
      "type": "reply",
      "replyNo": 5,
      "replyGroup": 3,
      "replyDepth": 0,
      "sCharacter": { "no": 0, "index": 1 },
      "content": "たまにはシャーレの方に来てみる？",
      "isFirst": false,
      "file": ""
    },
    {
      "type": "chat",
      "replyNo": 0,
      "replyGroup": 0,
      "replyDepth": 4,
      "sCharacter": { "no": 64, "index": 1 },
      "content": "うん",
      "isFirst": true,
      "file": ""
    },
    {
      "type": "chat",
      "replyNo": 0,
      "replyGroup": 0,
      "replyDepth": 5,
      "sCharacter": { "no": 64, "index": 1 },
      "content": "な、ななな何を言ってるの！？",
      "isFirst": true,
      "file": ""
    },
    {
      "type": "chat",
      "replyNo": 0,
      "replyGroup": 0,
      "replyDepth": 5,
      "sCharacter": { "no": 64, "index": 1 },
      "content": "そ、そういう風に誘導しても無駄だから",
      "isFirst": false,
      "file": ""
    },
    {
      "type": "chat",
      "replyNo": 0,
      "replyGroup": 0,
      "replyDepth": 0,
      "sCharacter": { "no": 64, "index": 1 },
      "content": "と、とにかく来て……",
      "isFirst": true,
      "file": ""
    },
    {
      "type": "chat",
      "replyNo": 0,
      "replyGroup": 0,
      "replyDepth": 0,
      "sCharacter": { "no": 64, "index": 1 },
      "content": "学校で待ってるから",
      "isFirst": false,
      "file": ""
    },
    {
      "type": "heart",
      "replyNo": 0,
      "replyGroup": 0,
      "replyDepth": 0,
      "sCharacter": { "no": 64, "index": 1 },
      "content": "",
      "isFirst": false,
      "file": ""
    },
    {
      "type": "chat",
      "replyNo": 0,
      "replyDepth": 0,
      "replyGroup": 0,
      "sCharacter": { "no": 64, "index": 1 },
      "content": "先生……",
      "isFirst": true,
      "file": ""
    },
    {
      "type": "chat",
      "replyNo": 0,
      "replyDepth": 0,
      "replyGroup": 0,
      "sCharacter": { "no": 64, "index": 1 },
      "content": "……先生？",
      "isFirst": true,
      "file": ""
    },
    {
      "type": "chat",
      "replyNo": 0,
      "replyGroup": 0,
      "replyDepth": 0,
      "sCharacter": { "no": 64, "index": 1 },
      "content": "さ",
      "isFirst": false,
      "file": ""
    },
    {
      "type": "chat",
      "replyNo": 0,
      "replyDepth": 0,
      "replyGroup": 0,
      "sCharacter": { "no": 64, "index": 1 },
      "content": "さっきの……その……",
      "isFirst": true,
      "file": ""
    },
    {
      "type": "chat",
      "replyNo": 0,
      "replyGroup": 0,
      "replyDepth": 0,
      "sCharacter": { "no": 64, "index": 1 },
      "content": "……？",
      "isFirst": false,
      "file": ""
    },
    {
      "type": "chat",
      "replyNo": 0,
      "replyGroup": 0,
      "replyDepth": 0,
      "sCharacter": { "no": 64, "index": 1 },
      "content": "……先生？",
      "isFirst": false,
      "file": ""
    },
    {
      "type": "chat",
      "replyNo": 0,
      "replyDepth": 0,
      "replyGroup": 0,
      "sCharacter": { "no": 64, "index": 1 },
      "content": "……",
      "isFirst": true,
      "file": ""
    },
    {
      "type": "chat",
      "replyNo": 0,
      "replyGroup": 0,
      "replyDepth": 0,
      "sCharacter": { "no": 64, "index": 1 },
      "content": "……もう寝ちゃった？",
      "isFirst": false,
      "file": ""
    }
  ]
]
