[
  {
    "title": "午後のティータイム",
    "nickname": "Molru",
    "date": "2023-02-22 22:58:13",
    "replyNo": 6,
    "replyGroup": 5,
    "chars": [62]
  },
  [
    {
      "type": "chat",
      "replyNo": 0,
      "replyGroup": 0,
      "replyDepth": 0,
      "sCharacter": { "no": 62, "index": 1 },
      "content": "ご無沙汰しております",
      "isFirst": true,
      "file": ""
    },
    {
      "type": "chat",
      "replyNo": 0,
      "replyDepth": 0,
      "replyGroup": 0,
      "sCharacter": { "no": 62, "index": 1 },
      "content": "ご機嫌いかがですか、先生？",
      "isFirst": true,
      "file": ""
    },
    {
      "type": "reply",
      "replyNo": 1,
      "replyGroup": 1,
      "replyDepth": 0,
      "sCharacter": { "no": 0, "index": 1 },
      "content": "ナギサ、久しぶり",
      "isFirst": true,
      "file": ""
    },
    {
      "type": "chat",
      "replyNo": 0,
      "replyGroup": 0,
      "replyDepth": 0,
      "sCharacter": { "no": 62, "index": 1 },
      "content": "はい、確かにお久しぶりですね",
      "isFirst": true,
      "file": ""
    },
    {
      "type": "chat",
      "replyNo": 0,
      "replyGroup": 0,
      "replyDepth": 0,
      "sCharacter": { "no": 62, "index": 1 },
      "content": "実は、トリニティの生徒たちのことでご相談したいことがありまして",
      "isFirst": false,
      "file": ""
    },
    {
      "type": "chat",
      "replyNo": 0,
      "replyDepth": 0,
      "replyGroup": 0,
      "sCharacter": { "no": 62, "index": 1 },
      "content": "それほど重たい内容でもありませんので、アフタヌーン・ティーでもご一緒しながらお話できればと思うのですが、いかがでしょうか？",
      "isFirst": true,
      "file": ""
    },
    {
      "type": "reply",
      "replyNo": 2,
      "replyGroup": 2,
      "replyDepth": 0,
      "sCharacter": { "no": 0, "index": 1 },
      "content": "あ、良いね。ぜひ",
      "isFirst": true,
      "file": ""
    },
    {
      "type": "chat",
      "replyNo": 0,
      "replyGroup": 0,
      "replyDepth": 0,
      "sCharacter": { "no": 62, "index": 1 },
      "content": "ふふっ",
      "isFirst": true,
      "file": ""
    },
    {
      "type": "chat",
      "replyNo": 0,
      "replyDepth": 0,
      "replyGroup": 0,
      "sCharacter": { "no": 62, "index": 1 },
      "content": "それでは、良い茶葉をご用意してお待ちしておりますね",
      "isFirst": true,
      "file": ""
    },
    {
      "type": "heart",
      "replyNo": 0,
      "replyGroup": 0,
      "replyDepth": 0,
      "sCharacter": { "no": 62, "index": 1 },
      "content": "",
      "isFirst": false,
      "file": ""
    },
    {
      "type": "chat",
      "replyNo": 0,
      "replyGroup": 0,
      "replyDepth": 0,
      "sCharacter": { "no": 62, "index": 1 },
      "content": "先に席を外してしまい、申し訳ございません。先生",
      "isFirst": true,
      "file": ""
    },
    {
      "type": "chat",
      "replyNo": 0,
      "replyDepth": 0,
      "replyGroup": 0,
      "sCharacter": { "no": 62, "index": 1 },
      "content": "急に体調が悪くなってしまい……健康管理ができておらず申し訳ありません",
      "isFirst": true,
      "file": ""
    },
    {
      "type": "reply",
      "replyNo": 3,
      "replyGroup": 3,
      "replyDepth": 0,
      "sCharacter": { "no": 0, "index": 1 },
      "content": "大丈夫だよ、気にしないで",
      "isFirst": true,
      "file": ""
    },
    {
      "type": "reply",
      "replyNo": 4,
      "replyGroup": 4,
      "replyDepth": 0,
      "sCharacter": { "no": 0, "index": 1 },
      "content": "ペットボトルの紅茶、もしかして口に合わなかった？",
      "isFirst": true,
      "file": ""
    },
    {
      "type": "reply",
      "replyNo": 5,
      "replyGroup": 4,
      "replyDepth": 0,
      "sCharacter": { "no": 0, "index": 1 },
      "content": "無理強いしちゃったかな、ごめんね……",
      "isFirst": false,
      "file": ""
    },
    {
      "type": "chat",
      "replyNo": 0,
      "replyGroup": 0,
      "replyDepth": 0,
      "sCharacter": { "no": 62, "index": 1 },
      "content": "いいえ、大変興味深い経験でした。ありがとうございます……",
      "isFirst": true,
      "file": ""
    },
    {
      "type": "chat",
      "replyNo": 0,
      "replyDepth": 0,
      "replyGroup": 0,
      "sCharacter": { "no": 62, "index": 1 },
      "content": "ですが、今度からはいただく量を調節した方が良いかもしれませんね……",
      "isFirst": true,
      "file": ""
    }
  ]
]
