[
  {
    "title": "保安委員長の推理",
    "nickname": "Molru",
    "date": "2022-10-23 22:48:50",
    "replyNo": 2,
    "replyGroup": 2,
    "chars": [106]
  },
  [
    {
      "type": "chat",
      "replyNo": 0,
      "replyGroup": 0,
      "replyDepth": 0,
      "sCharacter": { "no": 106, "index": 1 },
      "content": "先生、例のスパイについての続報だ",
      "isFirst": true,
      "file": ""
    },
    {
      "type": "chat",
      "replyNo": 0,
      "replyDepth": 0,
      "replyGroup": 0,
      "sCharacter": { "no": 106, "index": 1 },
      "content": "どこぞの卑劣なスパイが、今度はチェリノ会長のプリンを盗んだようでな",
      "isFirst": true,
      "file": ""
    },
    {
      "type": "reply",
      "replyNo": 1,
      "replyGroup": 1,
      "replyDepth": 0,
      "sCharacter": { "no": 0, "index": 1 },
      "content": "それ、確実にスパイの仕業なの？",
      "isFirst": true,
      "file": ""
    },
    {
      "type": "chat",
      "replyNo": 0,
      "replyGroup": 0,
      "replyDepth": 0,
      "sCharacter": { "no": 106, "index": 1 },
      "content": "ああ、そうだ。何せレッドウィンター連邦学園の保安は、いつだって完璧だからな！",
      "isFirst": true,
      "file": ""
    },
    {
      "type": "chat",
      "replyNo": 0,
      "replyDepth": 0,
      "replyGroup": 0,
      "sCharacter": { "no": 106, "index": 1 },
      "content": "スパイでも忍び込んでいない限り、何か問題が起こるはずがない！",
      "isFirst": false,
      "file": ""
    },
    {
      "type": "chat",
      "replyNo": 0,
      "replyDepth": 0,
      "replyGroup": 0,
      "sCharacter": { "no": 106, "index": 1 },
      "content": "だから間違いなくスパイの仕業だろう",
      "isFirst": true,
      "file": ""
    },
    {
      "type": "chat",
      "replyNo": 0,
      "replyGroup": 0,
      "replyDepth": 0,
      "sCharacter": { "no": 106, "index": 1 },
      "content": "しかし、問題が生じていてな……どういうわけかチェリノ会長は、私がプリンを盗んだと思っておられるようなんだ",
      "isFirst": false,
      "file": ""
    },
    {
      "type": "chat",
      "replyNo": 0,
      "replyDepth": 0,
      "replyGroup": 0,
      "sCharacter": { "no": 106, "index": 1 },
      "content": "もちろん、心当たりがないわけではないが……",
      "isFirst": true,
      "file": ""
    },
    {
      "type": "chat",
      "replyNo": 0,
      "replyDepth": 0,
      "replyGroup": 0,
      "sCharacter": { "no": 106, "index": 1 },
      "content": "逆に良い機会だ。今度こそスパイを捕まえて、私の有能さと無罪を証明してやろう！",
      "isFirst": true,
      "file": ""
    },
    {
      "type": "heart",
      "replyNo": 0,
      "replyGroup": 0,
      "replyDepth": 0,
      "sCharacter": { "no": 106, "index": 1 },
      "content": "",
      "isFirst": false,
      "file": ""
    }
  ]
]
