[
  {
    "title": "その中を見ることはできずとも",
    "nickname": "Mollu",
    "date": "2023-01-31 20:28:53",
    "replyNo": 5,
    "replyGroup": 3,
    "chars": [2]
  },
  [
    {
      "type": "chat",
      "replyNo": 0,
      "replyGroup": 0,
      "replyDepth": 0,
      "sCharacter": { "no": 2, "index": 4 },
      "content": "海はいいよね",
      "isFirst": true,
      "file": ""
    },
    {
      "type": "chat",
      "replyNo": 0,
      "replyDepth": 0,
      "replyGroup": 0,
      "sCharacter": { "no": 2, "index": 4 },
      "content": "白い砂浜、どこまでも続く水平線……",
      "isFirst": true,
      "file": ""
    },
    {
      "type": "reply",
      "replyNo": 1,
      "replyGroup": 1,
      "replyDepth": 0,
      "sCharacter": { "no": 0, "index": 1 },
      "content": "詩的だね",
      "isFirst": true,
      "file": ""
    },
    {
      "type": "reply",
      "replyNo": 2,
      "replyGroup": 1,
      "replyDepth": 0,
      "sCharacter": { "no": 0, "index": 1 },
      "content": "海はいいよね",
      "isFirst": false,
      "file": ""
    },
    {
      "type": "chat",
      "replyNo": 0,
      "replyGroup": 0,
      "replyDepth": 0,
      "sCharacter": { "no": 2, "index": 4 },
      "content": "うへ……",
      "isFirst": true,
      "file": ""
    },
    {
      "type": "chat",
      "replyNo": 0,
      "replyDepth": 0,
      "replyGroup": 0,
      "sCharacter": { "no": 2, "index": 4 },
      "content": "えっと",
      "isFirst": true,
      "file": ""
    },
    {
      "type": "chat",
      "replyNo": 0,
      "replyDepth": 0,
      "replyGroup": 0,
      "sCharacter": { "no": 2, "index": 4 },
      "content": "ちょっと言ってみたかっただけ",
      "isFirst": true,
      "file": ""
    },
    {
      "type": "chat",
      "replyNo": 0,
      "replyGroup": 0,
      "replyDepth": 0,
      "sCharacter": { "no": 2, "index": 4 },
      "content": "特に深い意味はないよ",
      "isFirst": false,
      "file": ""
    },
    {
      "type": "heart",
      "replyNo": 0,
      "replyGroup": 0,
      "replyDepth": 0,
      "sCharacter": { "no": 2, "index": 4 },
      "content": "",
      "isFirst": true,
      "file": ""
    },
    {
      "type": "chat",
      "replyNo": 0,
      "replyDepth": 0,
      "replyGroup": 0,
      "sCharacter": { "no": 2, "index": 4 },
      "content": "そういえば先生",
      "isFirst": true,
      "file": ""
    },
    {
      "type": "chat",
      "replyNo": 0,
      "replyGroup": 0,
      "replyDepth": 0,
      "sCharacter": { "no": 2, "index": 4 },
      "content": "どこかで聞いたことがあるんだけど",
      "isFirst": false,
      "file": ""
    },
    {
      "type": "chat",
      "replyNo": 0,
      "replyDepth": 0,
      "replyGroup": 0,
      "sCharacter": { "no": 2, "index": 4 },
      "content": "さっきのボラみたいに",
      "isFirst": true,
      "file": ""
    },
    {
      "type": "chat",
      "replyNo": 0,
      "replyGroup": 0,
      "replyDepth": 0,
      "sCharacter": { "no": 2, "index": 4 },
      "content": "鯨もジャンプするって聞いたんだけど",
      "isFirst": false,
      "file": ""
    },
    {
      "type": "chat",
      "replyNo": 0,
      "replyGroup": 0,
      "replyDepth": 0,
      "sCharacter": { "no": 2, "index": 4 },
      "content": "それって",
      "isFirst": false,
      "file": ""
    },
    {
      "type": "chat",
      "replyNo": 0,
      "replyDepth": 0,
      "replyGroup": 0,
      "sCharacter": { "no": 2, "index": 4 },
      "content": "どれくらい待てば見れるんだろう？",
      "isFirst": true,
      "file": ""
    },
    {
      "type": "reply",
      "replyNo": 3,
      "replyGroup": 2,
      "replyDepth": 0,
      "sCharacter": { "no": 0, "index": 1 },
      "content": "沿岸では見れないんじゃないかな",
      "isFirst": true,
      "file": ""
    },
    {
      "type": "reply",
      "replyNo": 4,
      "replyGroup": 2,
      "replyDepth": 0,
      "sCharacter": { "no": 0, "index": 1 },
      "content": "遠い海の方に出たら見れるかな",
      "isFirst": false,
      "file": ""
    },
    {
      "type": "chat",
      "replyNo": 0,
      "replyGroup": 0,
      "replyDepth": 0,
      "sCharacter": { "no": 2, "index": 4 },
      "content": "……",
      "isFirst": true,
      "file": ""
    },
    {
      "type": "chat",
      "replyNo": 0,
      "replyGroup": 0,
      "replyDepth": 0,
      "sCharacter": { "no": 2, "index": 4 },
      "content": "うへ……ちょっと難しいなそれは",
      "isFirst": true,
      "file": ""
    },
    {
      "type": "chat",
      "replyNo": 0,
      "replyDepth": 0,
      "replyGroup": 0,
      "sCharacter": { "no": 2, "index": 4 },
      "content": "残念……",
      "isFirst": false
    },
    {
      "type": "chat",
      "replyNo": 0,
      "replyDepth": 0,
      "replyGroup": 0,
      "sCharacter": { "no": 2, "index": 4 },
      "content": "まあ、でも",
      "isFirst": true,
      "file": ""
    },
    {
      "type": "chat",
      "replyNo": 0,
      "replyGroup": 0,
      "replyDepth": 0,
      "sCharacter": { "no": 2, "index": 4 },
      "content": "機会があったら一緒に見に行こうよ",
      "isFirst": false,
      "file": ""
    },
    {
      "type": "chat",
      "replyNo": 0,
      "replyDepth": 0,
      "replyGroup": 0,
      "sCharacter": { "no": 2, "index": 4 },
      "content": "一緒に、ね",
      "isFirst": true,
      "file": ""
    }
  ]
]
