[
  {
    "title": "メイドカフェ（２）",
    "nickname": "Molru",
    "date": "2022-10-23 15:12:55",
    "replyNo": 3,
    "replyGroup": 2,
    "chars": [37]
  },
  [
    {
      "type": "chat",
      "replyNo": 0,
      "replyGroup": 0,
      "replyDepth": 0,
      "sCharacter": { "no": 37, "index": 1 },
      "content": "友人の用事は無事終わったらしい",
      "isFirst": true,
      "file": ""
    },
    {
      "type": "chat",
      "replyNo": 0,
      "replyDepth": 0,
      "replyGroup": 0,
      "sCharacter": { "no": 37, "index": 1 },
      "content": "これでもう、メイドカフェに代わりに行く必要もない",
      "isFirst": true,
      "file": ""
    },
    {
      "type": "reply",
      "replyNo": 1,
      "replyGroup": 1,
      "replyDepth": 0,
      "sCharacter": { "no": 0, "index": 1 },
      "content": "お疲れ様",
      "isFirst": true,
      "file": ""
    },
    {
      "type": "reply",
      "replyNo": 2,
      "replyGroup": 1,
      "replyDepth": 0,
      "sCharacter": { "no": 0, "index": 1 },
      "content": "最後にもう一度見たかった！",
      "isFirst": false,
      "file": ""
    },
    {
      "type": "chat",
      "replyNo": 0,
      "replyGroup": 0,
      "replyDepth": 1,
      "sCharacter": { "no": 37, "index": 1 },
      "content": "うん、大変だったけど、友達にもありがとうって言われたよ",
      "isFirst": true,
      "file": ""
    },
    {
      "type": "chat",
      "replyNo": 0,
      "replyGroup": 0,
      "replyDepth": 2,
      "sCharacter": { "no": 37, "index": 1 },
      "content": "残念だけど、もう私がメイドカフェで仕事をすることはないから",
      "isFirst": true,
      "file": ""
    },
    {
      "type": "chat",
      "replyNo": 0,
      "replyGroup": 0,
      "replyDepth": 0,
      "sCharacter": { "no": 37, "index": 1 },
      "content": "もう先生にあの、萌え萌えキュンもやってあげられないね",
      "isFirst": true,
      "file": ""
    },
    {
      "type": "chat",
      "replyNo": 0,
      "replyDepth": 0,
      "replyGroup": 0,
      "sCharacter": { "no": 37, "index": 1 },
      "content": "残念……だったり、する？",
      "isFirst": true,
      "file": ""
    },
    {
      "type": "heart",
      "replyNo": 0,
      "replyGroup": 0,
      "replyDepth": 0,
      "sCharacter": { "no": 37, "index": 1 },
      "content": "",
      "isFirst": false,
      "file": ""
    },
    {
      "type": "chat",
      "replyNo": 0,
      "replyDepth": 0,
      "replyGroup": 0,
      "sCharacter": { "no": 37, "index": 1 },
      "content": "…なんてね。何にせよこれからもよろしく",
      "isFirst": true,
      "file": ""
    },
    {
      "type": "chat",
      "replyNo": 0,
      "replyDepth": 0,
      "replyGroup": 0,
      "sCharacter": { "no": 37, "index": 1 },
      "content": "私の、ご主人様",
      "isFirst": true,
      "file": ""
    }
  ]
]
