[
  {
    "title": "禁じられた研究",
    "nickname": "Molru",
    "date": "2022-10-22 21:05:14",
    "replyNo": 4,
    "replyGroup": 3,
    "chars": [18]
  },
  [
    {
      "type": "chat",
      "replyNo": 0,
      "replyGroup": 0,
      "replyDepth": 0,
      "sCharacter": { "no": 18, "index": 1 },
      "content": "美食の探究は今日も続く……予定だったのですが",
      "isFirst": true,
      "file": ""
    },
    {
      "type": "chat",
      "replyNo": 0,
      "replyGroup": 0,
      "replyDepth": 0,
      "sCharacter": { "no": 18, "index": 1 },
      "content": "壁にぶつかってしまいました",
      "isFirst": true,
      "file": ""
    },
    {
      "type": "chat",
      "replyNo": 0,
      "replyGroup": 0,
      "replyDepth": 0,
      "sCharacter": { "no": 18, "index": 1 },
      "content": "この難問をどう解決すれば良いのか……少し考える必要がありますわね",
      "isFirst": false,
      "file": ""
    },
    {
      "type": "reply",
      "replyNo": 1,
      "replyGroup": 1,
      "replyDepth": 0,
      "sCharacter": { "no": 0, "index": 1 },
      "content": "どんな内容か分からないけど、頑張って！",
      "isFirst": true,
      "file": ""
    },
    {
      "type": "chat",
      "replyNo": 0,
      "replyGroup": 0,
      "replyDepth": 0,
      "sCharacter": { "no": 18, "index": 1 },
      "content": "ああ、良いことを思いつきました",
      "isFirst": true,
      "file": ""
    },
    {
      "type": "chat",
      "replyNo": 0,
      "replyGroup": 0,
      "replyDepth": 0,
      "sCharacter": { "no": 18, "index": 1 },
      "content": "先生、少々お手伝いしていただけませんでしょうか？",
      "isFirst": false,
      "file": ""
    },
    {
      "type": "chat",
      "replyNo": 0,
      "replyGroup": 0,
      "replyDepth": 0,
      "sCharacter": { "no": 18, "index": 1 },
      "content": "ゲヘナでお待ちしておりますね",
      "isFirst": true,
      "file": ""
    },
    {
      "type": "heart",
      "replyNo": 0,
      "replyGroup": 0,
      "replyDepth": 0,
      "sCharacter": { "no": 18, "index": 1 },
      "content": "",
      "isFirst": false,
      "file": ""
    },
    {
      "type": "chat",
      "replyNo": 0,
      "replyGroup": 0,
      "replyDepth": 0,
      "sCharacter": { "no": 18, "index": 1 },
      "content": "よく考えてみたら、料理酒でも良かったかもしれませんわね",
      "isFirst": true,
      "file": ""
    },
    {
      "type": "chat",
      "replyNo": 0,
      "replyGroup": 0,
      "replyDepth": 0,
      "sCharacter": { "no": 18, "index": 1 },
      "content": "料理酒とぶどうジュース、次はこれで試してみましょうか",
      "isFirst": false,
      "file": ""
    },
    {
      "type": "reply",
      "replyNo": 2,
      "replyGroup": 2,
      "replyDepth": 0,
      "sCharacter": { "no": 0, "index": 1 },
      "content": "気をつけて料理してね……",
      "isFirst": true,
      "file": ""
    },
    {
      "type": "reply",
      "replyNo": 3,
      "replyGroup": 2,
      "replyDepth": 0,
      "sCharacter": { "no": 0, "index": 1 },
      "content": "安全第一でね……",
      "isFirst": false,
      "file": ""
    },
    {
      "type": "chat",
      "replyNo": 0,
      "replyGroup": 0,
      "replyDepth": 0,
      "sCharacter": { "no": 18, "index": 1 },
      "content": "ふふ、心配してくださるのですか？",
      "isFirst": true,
      "file": ""
    },
    {
      "type": "chat",
      "replyNo": 0,
      "replyGroup": 0,
      "replyDepth": 0,
      "sCharacter": { "no": 18, "index": 1 },
      "content": "嬉しいですわね。ふふっ、ありがとうございます",
      "isFirst": false,
      "file": ""
    }
  ]
]
