[
  {
    "title": "닌자 소녀는 빛나고 싶어!(번역)",
    "nickname": "Molru",
    "date": "2022-10-27 01:53:43",
    "replyNo": 8,
    "replyGroup": 7,
    "chars": [93]
  },
  [
    {
      "type": "chat",
      "replyNo": 0,
      "replyGroup": 0,
      "replyDepth": 0,
      "sCharacter": { "no": 93, "index": 1 },
      "content": "맞다. 선생 공. 혹시 샬레의 사무실에 그게 있는지 찾아봐 줄 수 있어?",
      "isFirst": true,
      "file": ""
    },
    {
      "type": "reply",
      "replyNo": 1,
      "replyGroup": 1,
      "replyDepth": 0,
      "sCharacter": { "no": 0, "index": 1 },
      "content": "그거라니? 뭘 말이야?",
      "isFirst": true,
      "file": ""
    },
    {
      "type": "chat",
      "replyNo": 0,
      "replyGroup": 0,
      "replyDepth": 0,
      "sCharacter": { "no": 93, "index": 1 },
      "content": "그러니까 그거. 내가 자주 보는 만화책- <카마보코 돌풍전> 19권 말이야 ",
      "isFirst": true,
      "file": ""
    },
    {
      "type": "chat",
      "replyNo": 0,
      "replyGroup": 0,
      "replyDepth": 0,
      "sCharacter": { "no": 93, "index": 1 },
      "content": "부실에서 아무리 찾아봐도 보이지 않길래. 짚이는 곳이 거기뿐이더라고",
      "isFirst": false,
      "file": ""
    },
    {
      "type": "reply",
      "replyNo": 2,
      "replyGroup": 2,
      "replyDepth": 0,
      "sCharacter": { "no": 0, "index": 1 },
      "content": "어느새 샬레에 그런 물건을?!",
      "isFirst": true,
      "file": ""
    },
    {
      "type": "chat",
      "replyNo": 0,
      "replyGroup": 0,
      "replyDepth": 0,
      "sCharacter": { "no": 93, "index": 1 },
      "content": "응…? 그야 우리 부실. 일단은 임시고. 언제 백화요란 녀석들이 들이닥칠지 모르고",
      "isFirst": true,
      "file": ""
    },
    {
      "type": "chat",
      "replyNo": 0,
      "replyGroup": 0,
      "replyDepth": 0,
      "sCharacter": { "no": 93, "index": 1 },
      "content": "음양부 녀석들도 매번 시끄럽게 들쑤시고 있으니까",
      "isFirst": false,
      "file": ""
    },
    {
      "type": "chat",
      "replyNo": 0,
      "replyDepth": 0,
      "replyGroup": 0,
      "sCharacter": { "no": 93, "index": 1 },
      "content": "나의 닌자 두뇌를 써서 생각해 본 결과-",
      "isFirst": true,
      "file": ""
    },
    {
      "type": "chat",
      "replyNo": 0,
      "replyGroup": 0,
      "replyDepth": 0,
      "sCharacter": { "no": 93, "index": 1 },
      "content": "굿즈는 샬레에 보관한다. 응. 그게 합리적이란 결론을 내렸지",
      "isFirst": false,
      "file": ""
    },
    {
      "type": "reply",
      "replyNo": 3,
      "replyGroup": 3,
      "replyDepth": 0,
      "sCharacter": { "no": 0, "index": 1 },
      "content": "샬레는 창고가 아닙니다. 미치루 양….",
      "isFirst": true,
      "file": ""
    },
    {
      "type": "chat",
      "replyNo": 0,
      "replyGroup": 0,
      "replyDepth": 0,
      "sCharacter": { "no": 93, "index": 1 },
      "content": "아! 심심하면 선생 공도 봐도 되니까! 추천하거든! 카마보코 시리즈!",
      "isFirst": true,
      "file": ""
    },
    {
      "type": "chat",
      "replyNo": 0,
      "replyGroup": 0,
      "replyDepth": 0,
      "sCharacter": { "no": 93, "index": 1 },
      "content": "그리고 말 나온 김에 전해두는 건데. 오늘 밤엔 공원에서 집합이니까. 까먹지 마?",
      "isFirst": false,
      "file": ""
    },
    {
      "type": "chat",
      "replyNo": 0,
      "replyDepth": 0,
      "replyGroup": 0,
      "sCharacter": { "no": 93, "index": 1 },
      "content": "그럼 기다리고 있겠소이다! 선생 공!",
      "isFirst": true,
      "file": ""
    },
    {
      "type": "reply",
      "replyNo": 4,
      "replyGroup": 4,
      "replyDepth": 0,
      "sCharacter": { "no": 0, "index": 1 },
      "content": "화제 전환 빠르구만! ",
      "isFirst": true,
      "file": ""
    },
    {
      "type": "reply",
      "replyNo": 5,
      "replyGroup": 4,
      "replyDepth": 0,
      "sCharacter": { "no": 0, "index": 1 },
      "content": "그건 좋은데, 오늘 밤엔 뭘 하려고…?",
      "isFirst": false,
      "file": ""
    },
    {
      "type": "chat",
      "replyNo": 0,
      "replyGroup": 0,
      "replyDepth": 0,
      "sCharacter": { "no": 93, "index": 1 },
      "content": "(파바바바바바밧!!!) <- 신발 끈 묶는 소리",
      "isFirst": true,
      "file": ""
    },
    {
      "type": "reply",
      "replyNo": 6,
      "replyGroup": 5,
      "replyDepth": 0,
      "sCharacter": { "no": 0, "index": 1 },
      "content": "이젠 닌자의 행동조차 아니지 않아…?!",
      "isFirst": true,
      "file": ""
    },
    {
      "type": "heart",
      "replyNo": 0,
      "replyGroup": 0,
      "replyDepth": 0,
      "sCharacter": { "no": 93, "index": 1 },
      "content": "",
      "isFirst": false,
      "file": ""
    },
    {
      "type": "chat",
      "replyNo": 0,
      "replyGroup": 0,
      "replyDepth": 0,
      "sCharacter": { "no": 93, "index": 1 },
      "content": "…선생 공, 어제 그거 때문인 건지. ",
      "isFirst": true,
      "file": ""
    },
    {
      "type": "chat",
      "replyNo": 0,
      "replyDepth": 0,
      "replyGroup": 0,
      "sCharacter": { "no": 93, "index": 1 },
      "content": "소생……. 감기에 걸려버렸소이다….",
      "isFirst": true,
      "file": ""
    },
    {
      "type": "reply",
      "replyNo": 7,
      "replyGroup": 6,
      "replyDepth": 0,
      "sCharacter": { "no": 0, "index": 1 },
      "content": "…알았어. 가서 죽 만들어줄 테니까.",
      "isFirst": true,
      "file": ""
    },
    {
      "type": "chat",
      "replyNo": 0,
      "replyGroup": 0,
      "replyDepth": 0,
      "sCharacter": { "no": 93, "index": 1 },
      "content": "그… 으응, 고, 고마워. 선생 공.",
      "isFirst": true,
      "file": ""
    },
    {
      "type": "chat",
      "replyNo": 0,
      "replyGroup": 0,
      "replyDepth": 0,
      "sCharacter": { "no": 93, "index": 1 },
      "content": "기, 기다리고 있겠습니다아….",
      "isFirst": false,
      "file": ""
    }
  ]
]
